{
  "name": "Mapa Padrão",
  "worldSize": 2048,
  "image": "maps/default_bg.png",
  "walls": [
    { "x": 512, "y": 512, "w": 64, "h": 512 },
    { "x": 1472, "y": 512, "w": 64, "h": 512 },
    { "x": 512, "y": 512, "w": 1024, "h": 64 },
    { "x": 512, "y": 960, "w": 1024, "h": 64 }
  ],
  "lowObstacles": [
    { "x": 960, "y": 700, "w": 128, "h": 128 }
  ],
  "spawnPoints": [
    { "x": 160, "y": 160 },
    { "x": 1888, "y": 160 },
    { "x": 160, "y": 1888 },
    { "x": 1888, "y": 1888 }
  ],
  "pointLights": [
    { "x": 1024, "y": 1024, "range": 600, "color": "#ffaa44" },
    { "x": 200, "y": 200, "range": 400, "color": "#44aaff" }
  ]
}
